README.rst
setup.py
fabutils/__init__.py
fabutils/context.py
fabutils/decorators.py
fabutils/env.py
fabutils/exceptions.py
fabutils/tasks.py
fabutils/text.py
fabutils/utils.py
vo_fabutils.egg-info/PKG-INFO
vo_fabutils.egg-info/SOURCES.txt
vo_fabutils.egg-info/dependency_links.txt
vo_fabutils.egg-info/requires.txt
vo_fabutils.egg-info/top_level.txt