Metadata-Version: 1.1
Name: vo-fabutils
Version: 0.1.3
Summary: Utilities for creating better fabric tasks.
Home-page: https://github.com/vinco/fabutils
Author: Vinco Orbis
Author-email: pypi@manoderecha.mx
License: Apache License (2.0)
Platform: UNKNOWN
Classifier: Development Status :: 4 - Beta
Classifier: Environment :: Console
Classifier: Intended Audience :: Developers
Classifier: License :: OSI Approved :: Apache Software License
Classifier: Operating System :: OS Independent
Classifier: Programming Language :: Python
Classifier: Topic :: Software Development :: Libraries :: Python Modules
Classifier: Topic :: Utilities
